skill_ovos_weather/LICENSE
skill_ovos_weather/MANIFEST.in
skill_ovos_weather/README.md
skill_ovos_weather/__init__.py
skill_ovos_weather/settingsmeta.json
skill_ovos_weather/version.py
skill_ovos_weather/locale/ca-es/dialog/and.dialog
skill_ovos_weather/locale/ca-es/dialog/percentage-number.dialog
skill_ovos_weather/locale/ca-es/dialog/condition/ash.dialog
skill_ovos_weather/locale/ca-es/dialog/condition/clear.dialog
skill_ovos_weather/locale/ca-es/dialog/condition/clouds.dialog
skill_ovos_weather/locale/ca-es/dialog/condition/drizzle.dialog
skill_ovos_weather/locale/ca-es/dialog/condition/dust.dialog
skill_ovos_weather/locale/ca-es/dialog/condition/haze.dialog
skill_ovos_weather/locale/ca-es/dialog/condition/mist.dialog
skill_ovos_weather/locale/ca-es/dialog/condition/rain.dialog
skill_ovos_weather/locale/ca-es/dialog/condition/smoke.dialog
skill_ovos_weather/locale/ca-es/dialog/condition/snow.dialog
skill_ovos_weather/locale/ca-es/dialog/condition/squall.dialog
skill_ovos_weather/locale/ca-es/dialog/condition/thunderstorm.dialog
skill_ovos_weather/locale/ca-es/dialog/condition/tornado.dialog
skill_ovos_weather/locale/ca-es/dialog/current/current-condition-expected-local.dialog
skill_ovos_weather/locale/ca-es/dialog/current/current-condition-expected-location.dialog
skill_ovos_weather/locale/ca-es/dialog/daily/daily-condition-expected-location.dialog
skill_ovos_weather/locale/ca-es/dialog/daily/daily-wind-light-loaction.dialog
skill_ovos_weather/locale/ca-es/dialog/direction/east.dialog
skill_ovos_weather/locale/ca-es/dialog/direction/north.dialog
skill_ovos_weather/locale/ca-es/dialog/direction/northeast.dialog
skill_ovos_weather/locale/ca-es/dialog/direction/northwest.dialog
skill_ovos_weather/locale/ca-es/dialog/direction/south.dialog
skill_ovos_weather/locale/ca-es/dialog/direction/southeast.dialog
skill_ovos_weather/locale/ca-es/dialog/direction/southwest.dialog
skill_ovos_weather/locale/ca-es/dialog/direction/west.dialog
skill_ovos_weather/ovos_skill_weather.egg-info/PKG-INFO
skill_ovos_weather/ovos_skill_weather.egg-info/SOURCES.txt
skill_ovos_weather/ovos_skill_weather.egg-info/dependency_links.txt
skill_ovos_weather/ovos_skill_weather.egg-info/entry_points.txt
skill_ovos_weather/ovos_skill_weather.egg-info/requires.txt
skill_ovos_weather/ovos_skill_weather.egg-info/top_level.txt
ovos_skill_weather-0.0.1a8.dist-info/LICENSE
ovos_skill_weather-0.0.1a8.dist-info/METADATA
ovos_skill_weather-0.0.1a8.dist-info/WHEEL
ovos_skill_weather-0.0.1a8.dist-info/entry_points.txt
ovos_skill_weather-0.0.1a8.dist-info/top_level.txt
ovos_skill_weather-0.0.1a8.dist-info/RECORD
