Metadata-Version: 2.1
Name: ovos-skill-weather
Version: 0.0.1a8
Summary: ovos skill plugin
Home-page: https://github.com/OpenVoiceOS/skill-ovos-weather
Author: JarbasAi
Author-email: jarbasai@mailfence.com
License: Apache-2.0
Keywords: ovos skill plugin
Platform: UNKNOWN
Requires-Dist: requests
Requires-Dist: pytz
Requires-Dist: ovos-utils (>=0.0.28a4,~=0.0)
Requires-Dist: ovos-workshop (>=0.0.12a27,~=0.0)
Provides-Extra: test
Requires-Dist: pytest ; extra == 'test'
Requires-Dist: pytest-cov ; extra == 'test'
Requires-Dist: pytest-timeout ; extra == 'test'
Requires-Dist: ovos-core[skills_lgpl] (>=0.0.5a28) ; extra == 'test'
Requires-Dist: ovos-plugin-manager ; extra == 'test'
Requires-Dist: ovos-skills-manager ; extra == 'test'
